mosamaticdesktop/__init__.py
mosamaticdesktop/__main__.py
mosamaticdesktop/app.py
mosamaticdesktop/core/__init__.py
mosamaticdesktop/core/data/__init__.py
mosamaticdesktop/core/data/data.py
mosamaticdesktop/core/data/datamanager.py
mosamaticdesktop/core/data/datamanagerlistener.py
mosamaticdesktop/core/data/dicomfiledata.py
mosamaticdesktop/core/data/dicomseriesdata.py
mosamaticdesktop/core/data/filedata.py
mosamaticdesktop/core/data/multidicomfiledata.py
mosamaticdesktop/core/data/multidicomseriesdata.py
mosamaticdesktop/core/loaders/__init__.py
mosamaticdesktop/core/loaders/dicomfileloader.py
mosamaticdesktop/core/loaders/dicomseriesloader.py
mosamaticdesktop/core/loaders/fileloader.py
mosamaticdesktop/core/loaders/loader.py
mosamaticdesktop/core/loaders/multidicomfileloader.py
mosamaticdesktop/core/loaders/multidicomseriesloader.py
mosamaticdesktop/core/singleton.py
mosamaticdesktop/core/utils/___init__.py
mosamaticdesktop/core/utils/functions.py
mosamaticdesktop/core/utils/logmanager.py
mosamaticdesktop/core/utils/logmanagerlistener.py
mosamaticdesktop/resources/VERSION
mosamaticdesktop/resources/icons/mosamaticdesktop.icns
mosamaticdesktop/resources/icons/mosamaticdesktop.ico
mosamaticdesktop/resources/icons/spinner.gif
mosamaticdesktop/resources/images/body-composition.jpg
mosamaticdesktop/ui/__init__.py
mosamaticdesktop/ui/components/__init__.py
mosamaticdesktop/ui/components/splashscreen.py
mosamaticdesktop/ui/dialogs/__init__.py
mosamaticdesktop/ui/dialogs/dialog.py
mosamaticdesktop/ui/dialogs/helpdialog.py
mosamaticdesktop/ui/dialogs/loaddicomfiledialog.py
mosamaticdesktop/ui/dialogs/loadfiledialog.py
mosamaticdesktop/ui/dialogs/loadfilesetdialog.py
mosamaticdesktop/ui/dialogs/loadmultidicomfiledialog.py
mosamaticdesktop/ui/mainwindow.py
mosamaticdesktop/ui/panels/__init__.py
mosamaticdesktop/ui/panels/datapanel.py
mosamaticdesktop/ui/panels/defaultpanel.py
mosamaticdesktop/ui/panels/logpanel.py
mosamaticdesktop/ui/panels/mainpanel.py
mosamaticdesktop_macos-2.0.3.dist-info/LICENSE
mosamaticdesktop_macos-2.0.3.dist-info/METADATA
mosamaticdesktop_macos-2.0.3.dist-info/WHEEL
mosamaticdesktop_macos-2.0.3.dist-info/entry_points.txt
mosamaticdesktop_macos-2.0.3.dist-info/RECORD
