Metadata-Version: 2.3
Name: mosamaticdesktop-macos
Version: 2.0.3
Summary: Desktop application for analyzing body composition in CT images (MacOS version)
License: MIT
Author: Ralph Brecheisen
Author-email: ralph.brecheisen@gmail.com
Requires-Python: >=3.9,<3.12
Classifier: License :: OSI Approved :: MIT License
Classifier: Programming Language :: Python :: 3
Classifier: Programming Language :: Python :: 3.9
Classifier: Programming Language :: Python :: 3.10
Classifier: Programming Language :: Python :: 3.11
Requires-Dist: click (<8.1.8)
Requires-Dist: mosamatic-cli-macos (>=1.6)
Requires-Dist: openpyxl (>=3.1.5,<4.0.0)
Requires-Dist: pandas (>=2.3.1,<3.0.0)
Requires-Dist: pendulum (>=3.1.0,<4.0.0)
Requires-Dist: pillow (>=11.3.0,<12.0.0)
Requires-Dist: poetry (>=2.1.4,<3.0.0)
Requires-Dist: pyside6-essentials (>=6.9)
Requires-Dist: pytest (>=8.4.1,<9.0.0)
Requires-Dist: python-gdcm (>=3.0.26,<4.0.0)
Requires-Dist: tensorboard (==2.15.2)
Requires-Dist: tensorboard-data-server (==0.7.2)
Requires-Dist: tensorflow (==2.15.0)
Requires-Dist: tensorflow-macos (==2.15.0)
Requires-Dist: torch (>=2.8.0,<3.0.0)
Requires-Dist: torchvision (>=0.23.0,<0.24.0)
